forkwork/forkwork.py
forkwork-0.0.5.dist-info/entry_points.txt
forkwork-0.0.5.dist-info/LICENSE
forkwork-0.0.5.dist-info/WHEEL
forkwork-0.0.5.dist-info/METADATA
forkwork-0.0.5.dist-info/RECORD
