Metadata-Version: 2.1
Name: forkwork
Version: 0.0.5
Summary: Find maintained forks of your favorite repositories
Home-page: https://github.com/github-tooling/forkwork
License: MIT
Author: Andriy Orehov
Author-email: andriyorehov@gmail.com
Requires-Python: >=3.5,<4.0
Classifier: License :: OSI Approved :: MIT License
Classifier: Programming Language :: Python :: 3
Classifier: Programming Language :: Python :: 3.5
Classifier: Programming Language :: Python :: 3.6
Classifier: Programming Language :: Python :: 3.7
Requires-Dist: cachecontrol (>=0.12.5,<0.13.0)
Requires-Dist: click (>=7.0,<8.0)
Requires-Dist: github3.py (>=1.3,<2.0)
Requires-Dist: halo (>=0.0.26,<0.0.27)
Requires-Dist: lockfile (>=0.12.2,<0.13.0)
Requires-Dist: pendulum (>=2.0,<3.0)
Requires-Dist: tabulate (>=0.8.3,<0.9.0)
